pylint_pydantic/__init__.py
pylint_pydantic/field.py
pylint_pydantic-0.4.0.dist-info/LICENSE
pylint_pydantic-0.4.0.dist-info/METADATA
pylint_pydantic-0.4.0.dist-info/WHEEL
pylint_pydantic-0.4.0.dist-info/top_level.txt
pylint_pydantic-0.4.0.dist-info/RECORD
