Metadata-Version: 2.1
Name: pylint-pydantic
Version: 0.4.0
Summary: A Pylint plugin to help Pylint understand the Pydantic
Home-page: https://github.com/fcfangcc/pylint-pydantic
Author: fcfangcc
Author-email: swjfc22@163.com
License: GPLv3
Keywords: pylint,pydantic
Platform: UNKNOWN
Classifier: Environment :: Console
Classifier: Intended Audience :: Developers
Classifier: Topic :: Software Development :: Quality Assurance
Classifier: Programming Language :: Python :: 3.10
Classifier: Programming Language :: Python :: 3.11
Classifier: Programming Language :: Python :: 3.12
Classifier: Programming Language :: Python :: 3.13
Requires-Python: >=3.10
License-File: LICENSE
Requires-Dist: pylint<5.0,>2.0
Requires-Dist: pydantic<3.0
Requires-Dist: pylint-plugin-utils
